fxy/CAS.py
fxy/LAB.py
fxy/__init__.py
fxy/__main__.py
fxy/__scipy__.py
fxy/__sklearn__.py
fxy/_a.py
fxy/_f.py
fxy/_l.py
fxy/_n.py
fxy/_p.py
fxy/_plotting_.py
fxy/_s.py
fxy/_scipy.py
fxy/_sklearn.py
fxy/a.py
fxy/calc.py
fxy/cas.py
fxy/f.py
fxy/install.py
fxy/kernels.py
fxy/l.py
fxy/lab.py
fxy/math.py
fxy/n.py
fxy/p.py
fxy/physics.py
fxy/plot.py
fxy/s.py
fxy/statistics.py
fxy/stats.py
fxy/__paste__/__init__.py
fxy-0.7.7.dist-info/METADATA
fxy-0.7.7.dist-info/WHEEL
fxy-0.7.7.dist-info/entry_points.txt
fxy-0.7.7.dist-info/top_level.txt
fxy-0.7.7.dist-info/RECORD
