Metadata-Version: 2.1
Name: fxy
Version: 0.7.7
Summary: Convenience imports and scientific functions.
Home-page: https://github.com/mindey/fxy
Author: Mindey
Author-email: mindey@mindey.com
License: UNLICENSE
Requires-Dist: PyQt5
Requires-Dist: appdirs
Requires-Dist: eday
Requires-Dist: ipython
Requires-Dist: jupyter-client
Requires-Dist: matplotlib
Requires-Dist: mpmath
Requires-Dist: qtconsole
Requires-Dist: scikit-learn
Requires-Dist: scipy
Requires-Dist: seaborn
Requires-Dist: statsmodels
Requires-Dist: sympy
Requires-Dist: xarray
Requires-Dist: windows-curses>=2.2.0; platform_system == "Windows"
Provides-Extra: test
Requires-Dist: coverage; extra == "test"
Requires-Dist: pytest; extra == "test"
Requires-Dist: pytest-cov; extra == "test"
